pydgram/__init__.py
pydgram/DGram.pyd
pydgram/DGram.so
pydgram-0.0.1rc10.dist-info/WHEEL
pydgram-0.0.1rc10.dist-info/METADATA
pydgram-0.0.1rc10.dist-info/RECORD
