Metadata-Version: 2.1
Name: pydgram
Version: 0.0.1rc10
Summary: 
Author: DesKaOne
Author-email: DesKaOne@users.noreply.github.com
Requires-Python: >=3.8,<4.0
Classifier: Programming Language :: Python :: 3
Classifier: Programming Language :: Python :: 3.8
Classifier: Programming Language :: Python :: 3.9
Classifier: Programming Language :: Python :: 3.10
Classifier: Programming Language :: Python :: 3.11
Requires-Dist: master-tuyul-sdk (>=0.1.2,<0.2.0)
Requires-Dist: pyrogram (>=2.0.106,<3.0.0)
